pyNfsClient/__info__.py
pyNfsClient/__init__.py
pyNfsClient/const.py
pyNfsClient/mount.py
pyNfsClient/nfs3.py
pyNfsClient/nfs4.py
pyNfsClient/pack.py
pyNfsClient/portmap.py
pyNfsClient/rpc.py
pyNfsClient/rtypes.py
pyNfsClient/utils.py
pyNfsClient-0.1.5.dist-info/LICENSE
pyNfsClient-0.1.5.dist-info/METADATA
pyNfsClient-0.1.5.dist-info/WHEEL
pyNfsClient-0.1.5.dist-info/top_level.txt
pyNfsClient-0.1.5.dist-info/RECORD
