Metadata-Version: 2.1
Name: pyNfsClient
Version: 0.1.5
Summary: Pure python NFS client
Home-page: https://github.com/CharmingYang0/NfsClient
Author: Cooper Yang
Author-email: cm_yang@yeah.net
License: MIT
Keywords: RPC NFS struct
Platform: any
Classifier: Development Status :: 3 - Alpha
Classifier: Intended Audience :: Developers
Classifier: License :: OSI Approved :: MIT License
Classifier: Operating System :: OS Independent
Classifier: Topic :: System :: Filesystems
Classifier: Topic :: Software Development :: Libraries :: Python Modules
Classifier: Natural Language :: English
Classifier: Programming Language :: Python :: 2.7
Classifier: Programming Language :: Python :: 3.6
Classifier: Programming Language :: Python :: 3.7
Requires-Python: >=2.7
